fyers_token_manager_v3/__init__.py
fyers_token_manager_v3-0.1.1.dist-info/LICENSE
fyers_token_manager_v3-0.1.1.dist-info/METADATA
fyers_token_manager_v3-0.1.1.dist-info/WHEEL
fyers_token_manager_v3-0.1.1.dist-info/top_level.txt
fyers_token_manager_v3-0.1.1.dist-info/RECORD
