Metadata-Version: 2.1
Name: fyers-token-manager-v3
Version: 0.1.1
Summary: Fyers Token Manager
Home-page: https://github.com/krunaldodiya/fyers_token_manager
Author: Krunal Dodiya
Author-email: kunal.dodiya1@gmail.com
License: UNKNOWN
Platform: UNKNOWN
Classifier: Programming Language :: Python :: 3
Classifier: Operating System :: OS Independent
License-File: LICENSE
Requires-Dist: fyers-apiv3
Requires-Dist: pyotp
Requires-Dist: requests
